fp_bglss/__init__.py
fp_bglss/config.py
fp_bglss/configForward.py
fp_bglss/consts.py
fp_bglss/env.py
fp_bglss/logevent.py
fp_bglss/logeventdaemon.py
fp_bglss/secret.py
fp_bglss-1.0.15.dist-info/METADATA
fp_bglss-1.0.15.dist-info/WHEEL
fp_bglss-1.0.15.dist-info/top_level.txt
fp_bglss-1.0.15.dist-info/RECORD
